TerminalAlert/__init__.py
TerminalAlert/main.py
TerminalAlert/utils.py
TerminalAlert/icons/failure.png
TerminalAlert/icons/favicon.ico
TerminalAlert/icons/logo.png
TerminalAlert/icons/success.png
TerminalAlert-1.2.1.dist-info/LICENSE
TerminalAlert-1.2.1.dist-info/METADATA
TerminalAlert-1.2.1.dist-info/WHEEL
TerminalAlert-1.2.1.dist-info/entry_points.txt
TerminalAlert-1.2.1.dist-info/top_level.txt
TerminalAlert-1.2.1.dist-info/RECORD
