Metadata-Version: 2.1
Name: TerminalAlert
Version: 1.2.1
Summary: Command Completion Alerts—Stay Notified, Stay Productive!
Author-email: "Emmanuel C. Jemeni" <jemenichinonso11@gmail.com>
License: MIT License
Project-URL: Homepage, https://github.com/Jemeni11/TerminalAlert
Project-URL: Bug Tracker, https://github.com/Jemeni11/TerminalAlert/issues
Project-URL: Changelog, https://github.com/Jemeni11/TerminalAlert/blob/main/CHANGELOG.md
Keywords: Command,Notifications,Terminal,Productivity,Automation,Success,Execution,Alerts,CLI,Multitasking
Classifier: Development Status :: 5 - Production/Stable
Classifier: Programming Language :: Python :: 3
Classifier: License :: OSI Approved :: MIT License
Classifier: Operating System :: OS Independent
Requires-Python: >=3.6
License-File: LICENSE
Requires-Dist: notify_py>=0.3.43
Requires-Dist: packaging>=24.2
